LICENSE
MANIFEST.in
README.md
setup.py
cbpi4_FermenterHysteresisWithChillerDiff/__init__.py
cbpi4_FermenterHysteresisWithChillerDiff/config.yaml
cbpi4_FermenterHysteresisWithChillerDiff.egg-info/PKG-INFO
cbpi4_FermenterHysteresisWithChillerDiff.egg-info/SOURCES.txt
cbpi4_FermenterHysteresisWithChillerDiff.egg-info/dependency_links.txt
cbpi4_FermenterHysteresisWithChillerDiff.egg-info/top_level.txt