Metadata-Version: 1.0
Name: cbpi4-FermenterHysteresisWithChillerDiff
Version: 0.0.3
Summary: CraftBeerPi Plugin
Home-page: https://github.com/mstrinzha/cbpi4_FermenterHysteresisWithChillerDiff
Author: Maxim Strinzha
Author-email: mstrinzha@gmail.com
License: UNKNOWN
Platform: UNKNOWN
